pycrypt/__init__.py
pycrypt/asymmetric/__init__.py
pycrypt/asymmetric/dh/__init__.py
pycrypt/asymmetric/dh/core.py
pycrypt/asymmetric/dh/groups.py
pycrypt/asymmetric/dh/keyformat.py
pycrypt/asymmetric/rsa/__init__.py
pycrypt/asymmetric/rsa/core.py
pycrypt/asymmetric/rsa/keyformat.py
pycrypt/asymmetric/rsa/utils.py
pycrypt/hash/__init__.py
pycrypt/hash/sha/__init__.py
pycrypt/hash/sha/core.py
pycrypt/hash/sha/hmac.py
pycrypt/hash/sha/variants.py
pycrypt/main.py
pycrypt/symmetric/__init__.py
pycrypt/symmetric/aes/__init__.py
pycrypt/symmetric/aes/core.py
pycrypt/symmetric/aes/modes.py
pycrypt/symmetric/aes/utils.py
pycrypt/utils/__init__.py
pycrypt/utils/asn1.py
pycrypt/utils/padding.py
pycrypt/utils/utils.py
pycrypt_lib-1.1.4.dist-info/WHEEL
pycrypt_lib-1.1.4.dist-info/METADATA
pycrypt_lib-1.1.4.dist-info/RECORD
