Metadata-Version: 2.3
Name: pycrypt-lib
Version: 1.1.4
Summary: A pure Python implementation of cryptographic primitives, written in a clean, Pythonic, and type-safe way.
Author: Aravindaksha Balaji
Author-email: Aravindaksha Balaji <aravindakshabalaji@gmail.com>
Requires-Dist: egcd>=3.0.0
Requires-Dist: primefac>=2.0.12
Requires-Python: >=3.9
Project-URL: Homepage, https://pycrypt-lib.readthedocs.io/en/latest/
Project-URL: Issues, https://github.com/aravindakshabalaji/pycrypt-lib/issues
Project-URL: Repository, https://github.com/aravindakshabalaji/pycrypt-lib
